{"tweet":{"twitter_entities":{"user_mentions":[{"screen_name":"N2eN2a", "indices":[8, 15], "id_str":"255372535", "name":"Dr.Nwanyiocha", "id":255372535}, {"screen_name":"deboadejugbe", "indices":[17, 30], "id_str":"42872795", "name":"Debo Adejugbe", "id":42872795}], "urls":[], "hashtags":[]}, "actor":{"location":null, "link":"http://www.twitter.com/deboadejugbe"}, "link":"http://twitter.com/deboadejugbe/statuses/184632863700951041", "body":"Hmm. RT\"@N2eN2a: @deboadejugbe Panadol for another man Headache? I think nt\"", "followers":357}}