{"tweet":{"twitter_entities":{"user_mentions":[{"screen_name":"managingmack", "indices":[27, 40], "id_str":"310839571", "name":"Jevon L Mack", "id":310839571}, {"screen_name":"definitelyRANDY", "indices":[42, 58], "id_str":"281299200", "name":"ran", "id":281299200}], "urls":[], "hashtags":[]}, "actor":{"location":null, "link":"http://www.twitter.com/definitelyRANDY"}, "link":"http://twitter.com/definitelyRANDY/statuses/182820788678832128", "body":"::sprays you with Lysol:: “@managingmack: @definitelyRANDY *Coughs*”", "followers":114}}