{"tweet":{"twitter_entities":{"user_mentions":[{"screen_name":"Jerkaholicgear", "indices":[0, 15], "id_str":"116607621", "name":"jerkaholic clothing", "id":116607621}, {"screen_name":"YouTube", "indices":[56, 64], "id_str":"10228272", "name":"YouTube", "id":10228272}], "urls":[{"display_url":"youtu.be/qPA89qVT7jo", "expanded_url":"http://youtu.be/qPA89qVT7jo", "indices":[31, 51], "url":"http://t.co/j2e1Acxr"}], "hashtags":[]}, "actor":{"location":null, "link":"http://www.twitter.com/superkillz7"}, "link":"http://twitter.com/superkillz7/statuses/183741085615538176", "body":"@Jerkaholicgear COLD HEART ;): http://t.co/j2e1Acxr via @youtube Shout out to Yung Incredible", "followers":1}}