{"tweet":{"twitter_entities":{"user_mentions":[{"screen_name":"rubicon49bc", "indices":[0, 12], "id_str":"15788716", "name":"Matt Pallotta", "id":15788716}], "urls":[{"display_url":"bz.lo.cr/P9u", "expanded_url":"http://bz.lo.cr/P9u", "indices":[113, 133], "url":"http://t.co/oLjjzIrX"}], "hashtags":[]}, "actor":{"location":{"displayName":"Chicago, IL", "objectType":"place"}, "link":"http://www.twitter.com/Walgreens"}, "link":"http://twitter.com/Walgreens/statuses/184765980998778880", "body":"@rubicon49bc Allergies? Take back Spring w/ HALLS Cough drops - they soothe allergy-related Cough & Sore throat: http://t.co/oLjjzIrX", "followers":90677}}