{"tweet":{"twitter_entities":{"user_mentions":[], "urls":[{"display_url":"migre.me/8plC4", "expanded_url":"http://migre.me/8plC4", "indices":[116, 136], "url":"http://t.co/HjrmEoTx"}], "hashtags":[]}, "actor":{"location":{"displayName":"US", "objectType":"place"}, "link":"http://www.twitter.com/RochelleMailer"}, "link":"http://twitter.com/RochelleMailer/statuses/183620091911479298", "body":"Justin Bieber Kids’ JB1040  Round Multi-Colored Dial Tie Dye Silicone Strap Watch: Take part of the Bieber Fever... http://t.co/HjrmEoTx", "followers":2816}}